[
  {
    "full_name": "LNReader/lnreader",
    "stargazers_count": 576,
    "open_issues_count": 56,
    "forks_count": 57
  },
  {
    "full_name": "zehfernandes/wordnote",
    "stargazers_count": 578,
    "open_issues_count": 16,
    "forks_count": 28
  },
  {
    "full_name": "microsoft/chart-parts",
    "stargazers_count": 594,
    "open_issues_count": 26,
    "forks_count": 34
  },
  {
    "full_name": "reactwg/react-native-new-architecture",
    "stargazers_count": 623,
    "open_issues_count": 0,
    "forks_count": 8
  },
  {
    "full_name": "OneKeyHQ/app-monorepo",
    "stargazers_count": 1201,
    "open_issues_count": 5,
    "forks_count": 165
  },
  {
    "full_name": "MetaMask/metamask-mobile",
    "stargazers_count": 1267,
    "open_issues_count": 669,
    "forks_count": 618
  },
  {
    "full_name": "n8n-io/n8n",
    "stargazers_count": 25629,
    "open_issues_count": 245,
    "forks_count": 2987
  },
  {
    "full_name": "portainer/portainer",
    "stargazers_count": 23128,
    "open_issues_count": 933,
    "forks_count": 2043
  },
  {
    "full_name": "photoprism/photoprism",
    "stargazers_count": 22578,
    "open_issues_count": 359,
    "forks_count": 1266
  },
  {
    "full_name": "zedeus/nitter",
    "stargazers_count": 5681,
    "open_issues_count": 119,
    "forks_count": 259
  },
  {
    "full_name": "nextcloud/server",
    "stargazers_count": 20194,
    "open_issues_count": 2567,
    "forks_count": 3223
  },
  {
    "full_name": "mantinedev/mantine-next-template",
    "stargazers_count": 225,
    "open_issues_count": 5,
    "forks_count": 47
  },
  {
    "full_name": "iv-org/invidious",
    "stargazers_count": 8347,
    "open_issues_count": 326,
    "forks_count": 753
  },
  {
    "full_name": "jellyfin/jellyfin",
    "stargazers_count": 16730,
    "open_issues_count": 877,
    "forks_count": 1641
  },
  {
    "full_name": "jellyfin/jellyfin-expo",
    "stargazers_count": 152,
    "open_issues_count": 42,
    "forks_count": 38
  },
  {
    "full_name": "jellyfin/jellyfin-web",
    "stargazers_count": 958,
    "open_issues_count": 244,
    "forks_count": 611
  },
  {
    "full_name": "firefly-iii/firefly-iii",
    "stargazers_count": 8941,
    "open_issues_count": 93,
    "forks_count": 924
  },
  {
    "full_name": "spikecodes/libreddit",
    "stargazers_count": 3472,
    "open_issues_count": 144,
    "forks_count": 183
  },
  {
    "full_name": "hay-kot/mealie",
    "stargazers_count": 2495,
    "open_issues_count": 70,
    "forks_count": 264
  },
  {
    "full_name": "meienberger/runtipi",
    "stargazers_count": 3991,
    "open_issues_count": 24,
    "forks_count": 79
  },
  {
    "full_name": "rtivital/omatsuri",
    "stargazers_count": 1888,
    "open_issues_count": 4,
    "forks_count": 132
  },
  {
    "full_name": "Charca/astro-movies",
    "stargazers_count": 57,
    "open_issues_count": 0,
    "forks_count": 12
  },
  {
    "full_name": "juliencrn/usehooks-ts",
    "stargazers_count": 2155,
    "open_issues_count": 23,
    "forks_count": 159
  },
  {
    "full_name": "jeanverster/chakra-ui-steps",
    "stargazers_count": 293,
    "open_issues_count": 15,
    "forks_count": 32
  },
  {
    "full_name": "aod/zhithead",
    "stargazers_count": 103,
    "open_issues_count": 2,
    "forks_count": 6
  },
  {
    "full_name": "typestack/class-validator",
    "stargazers_count": 8324,
    "open_issues_count": 422,
    "forks_count": 629
  },
  {
    "full_name": "pankod/refine",
    "stargazers_count": 3045,
    "open_issues_count": 18,
    "forks_count": 222
  },
  {
    "full_name": "notadd/notadd",
    "stargazers_count": 2636,
    "open_issues_count": 38,
    "forks_count": 391
  },
  {
    "full_name": "FaridSafi/react-native-gifted-chat",
    "stargazers_count": 11923,
    "open_issues_count": 75,
    "forks_count": 3400
  },
  {
    "full_name": "airbnb/lottie-android",
    "stargazers_count": 33227,
    "open_issues_count": 37,
    "forks_count": 5301
  }
]