[
  {
    "full_name": "joelparkerhenderson/architecture-decision-record",
    "stargazers_count": 7861,
    "open_issues_count": 1,
    "forks_count": 1894
  },
  {
    "full_name": "Aashu-Dubey/React-Native-UI-Templates",
    "stargazers_count": 573,
    "open_issues_count": 2,
    "forks_count": 85
  },
  {
    "full_name": "GetStream/react-native-samples",
    "stargazers_count": 76,
    "open_issues_count": 2,
    "forks_count": 30
  },
  {
    "full_name": "infinitered/reactotron",
    "stargazers_count": 13758,
    "open_issues_count": 124,
    "forks_count": 904
  },
  {
    "full_name": "creativetimofficial/argon-react-native",
    "stargazers_count": 560,
    "open_issues_count": 5,
    "forks_count": 298
  },
  {
    "full_name": "ant-design/ant-design-mobile-rn",
    "stargazers_count": 2596,
    "open_issues_count": 31,
    "forks_count": 581
  },
  {
    "full_name": "obytes/react-native-template-obytes",
    "stargazers_count": 477,
    "open_issues_count": 4,
    "forks_count": 77
  },
  {
    "full_name": "chatwoot/chatwoot-mobile-app",
    "stargazers_count": 364,
    "open_issues_count": 63,
    "forks_count": 140
  },
  {
    "full_name": "alexZajac/react-native-skeleton-content",
    "stargazers_count": 398,
    "open_issues_count": 8,
    "forks_count": 103
  },
  {
    "full_name": "EdgeApp/edge-react-gui",
    "stargazers_count": 392,
    "open_issues_count": 110,
    "forks_count": 245
  },
  {
    "full_name": "heylinda/heylinda-app",
    "stargazers_count": 462,
    "open_issues_count": 15,
    "forks_count": 115
  },
  {
    "full_name": "pagopa/io-app",
    "stargazers_count": 459,
    "open_issues_count": 30,
    "forks_count": 80
  },
  {
    "full_name": "grahammendick/navigation",
    "stargazers_count": 463,
    "open_issues_count": 1,
    "forks_count": 36
  },
  {
    "full_name": "pmndrs/its-fine",
    "stargazers_count": 621,
    "open_issues_count": 0,
    "forks_count": 5
  },
  {
    "full_name": "LNReader/lnreader",
    "stargazers_count": 602,
    "open_issues_count": 60,
    "forks_count": 63
  },
  {
    "full_name": "zehfernandes/wordnote",
    "stargazers_count": 586,
    "open_issues_count": 16,
    "forks_count": 29
  },
  {
    "full_name": "microsoft/chart-parts",
    "stargazers_count": 595,
    "open_issues_count": 26,
    "forks_count": 34
  },
  {
    "full_name": "reactwg/react-native-new-architecture",
    "stargazers_count": 633,
    "open_issues_count": 0,
    "forks_count": 8
  },
  {
    "full_name": "OneKeyHQ/app-monorepo",
    "stargazers_count": 1223,
    "open_issues_count": 9,
    "forks_count": 171
  },
  {
    "full_name": "MetaMask/metamask-mobile",
    "stargazers_count": 1300,
    "open_issues_count": 660,
    "forks_count": 637
  },
  {
    "full_name": "n8n-io/n8n",
    "stargazers_count": 26005,
    "open_issues_count": 247,
    "forks_count": 3030
  },
  {
    "full_name": "portainer/portainer",
    "stargazers_count": 23335,
    "open_issues_count": 967,
    "forks_count": 2056
  },
  {
    "full_name": "photoprism/photoprism",
    "stargazers_count": 22879,
    "open_issues_count": 360,
    "forks_count": 1291
  },
  {
    "full_name": "zedeus/nitter",
    "stargazers_count": 5830,
    "open_issues_count": 126,
    "forks_count": 267
  },
  {
    "full_name": "nextcloud/server",
    "stargazers_count": 20367,
    "open_issues_count": 2598,
    "forks_count": 3246
  },
  {
    "full_name": "mantinedev/mantine-next-template",
    "stargazers_count": 237,
    "open_issues_count": 7,
    "forks_count": 52
  },
  {
    "full_name": "iv-org/invidious",
    "stargazers_count": 8563,
    "open_issues_count": 318,
    "forks_count": 770
  },
  {
    "full_name": "jellyfin/jellyfin",
    "stargazers_count": 17007,
    "open_issues_count": 900,
    "forks_count": 1661
  },
  {
    "full_name": "jellyfin/jellyfin-expo",
    "stargazers_count": 154,
    "open_issues_count": 42,
    "forks_count": 37
  },
  {
    "full_name": "jellyfin/jellyfin-web",
    "stargazers_count": 974,
    "open_issues_count": 244,
    "forks_count": 628
  }
]